streamlit_kpi_metric/__init__.py
streamlit_kpi_metric-0.1.1.dist-info/WHEEL
streamlit_kpi_metric-0.1.1.dist-info/METADATA
streamlit_kpi_metric-0.1.1.dist-info/RECORD
