Metadata-Version: 2.1
Name: streamlit-kpi-metric
Version: 0.1.1
Summary: Library to create KPI metric for streamlit dashboards
Author: 100mi
Author-email: smtrgupta96@gmail.com
Requires-Python: >=3.7,<4.0
Classifier: Programming Language :: Python :: 3
Classifier: Programming Language :: Python :: 3.7
Classifier: Programming Language :: Python :: 3.8
Classifier: Programming Language :: Python :: 3.9
Requires-Dist: streamlit (>=0.86.0,<0.87.0)
